[
    {
        "colo": "Default",
        "ip": "2606:4700:3025:c953:c94b:b5ca:6a2f:fa93",
        "latency": 4,
        "line": "CM",
        "loss": 0,
        "node": "NETCUP",
        "speed": 411,
        "time": "2025-09-28 22:39:50"
    },
    {
        "colo": "Default",
        "ip": "2606:4700:3013:6101:9d39:905d:4073:ed2",
        "latency": 3,
        "line": "CM",
        "loss": 0,
        "node": "NETCUP",
        "speed": 408,
        "time": "2025-09-28 22:39:50"
    },
    {
        "colo": "Default",
        "ip": "2606:4700:3013:4150:c069:b9cc:6b81:49ff",
        "latency": 3,
        "line": "CM",
        "loss": 0,
        "node": "NETCUP",
        "speed": 404,
        "time": "2025-09-28 22:39:50"
    },
    {
        "colo": "Default",
        "ip": "2606:4700:3025:970d:fe0f:d9f1:72c0:5f6d",
        "latency": 3,
        "line": "CM",
        "loss": 0,
        "node": "NETCUP",
        "speed": 396,
        "time": "2025-09-28 22:39:51"
    },
    {
        "colo": "Default",
        "ip": "2606:4700:90c0:7be2:8829:b028:c9ff:b156",
        "latency": 3,
        "line": "CM",
        "loss": 0,
        "node": "NETCUP",
        "speed": 326,
        "time": "2025-09-28 22:39:51"
    },
    {
        "colo": "Default",
        "ip": "2606:4700:3025:c953:c94b:b5ca:6a2f:fa93",
        "latency": 4,
        "line": "CT",
        "loss": 0,
        "node": "NETCUP",
        "speed": 411,
        "time": "2025-09-28 22:39:50"
    },
    {
        "colo": "Default",
        "ip": "2606:4700:3013:6101:9d39:905d:4073:ed2",
        "latency": 3,
        "line": "CT",
        "loss": 0,
        "node": "NETCUP",
        "speed": 408,
        "time": "2025-09-28 22:39:50"
    },
    {
        "colo": "Default",
        "ip": "2606:4700:3013:4150:c069:b9cc:6b81:49ff",
        "latency": 3,
        "line": "CT",
        "loss": 0,
        "node": "NETCUP",
        "speed": 404,
        "time": "2025-09-28 22:39:50"
    },
    {
        "colo": "Default",
        "ip": "2606:4700:3025:970d:fe0f:d9f1:72c0:5f6d",
        "latency": 3,
        "line": "CT",
        "loss": 0,
        "node": "NETCUP",
        "speed": 396,
        "time": "2025-09-28 22:39:51"
    },
    {
        "colo": "Default",
        "ip": "2606:4700:90c0:7be2:8829:b028:c9ff:b156",
        "latency": 3,
        "line": "CT",
        "loss": 0,
        "node": "NETCUP",
        "speed": 326,
        "time": "2025-09-28 22:39:51"
    },
    {
        "colo": "Default",
        "ip": "2606:4700:3025:c953:c94b:b5ca:6a2f:fa93",
        "latency": 4,
        "line": "CU",
        "loss": 0,
        "node": "NETCUP",
        "speed": 411,
        "time": "2025-09-28 22:39:50"
    },
    {
        "colo": "Default",
        "ip": "2606:4700:3013:6101:9d39:905d:4073:ed2",
        "latency": 3,
        "line": "CU",
        "loss": 0,
        "node": "NETCUP",
        "speed": 408,
        "time": "2025-09-28 22:39:50"
    },
    {
        "colo": "Default",
        "ip": "2606:4700:3013:4150:c069:b9cc:6b81:49ff",
        "latency": 3,
        "line": "CU",
        "loss": 0,
        "node": "NETCUP",
        "speed": 404,
        "time": "2025-09-28 22:39:50"
    },
    {
        "colo": "Default",
        "ip": "2606:4700:3025:970d:fe0f:d9f1:72c0:5f6d",
        "latency": 3,
        "line": "CU",
        "loss": 0,
        "node": "NETCUP",
        "speed": 396,
        "time": "2025-09-28 22:39:51"
    },
    {
        "colo": "Default",
        "ip": "2606:4700:90c0:7be2:8829:b028:c9ff:b156",
        "latency": 3,
        "line": "CU",
        "loss": 0,
        "node": "NETCUP",
        "speed": 326,
        "time": "2025-09-28 22:39:51"
    }
]