[
    {
        "colo": "Default",
        "ip": "2606:4700:8dee:b95e:2ae3:bfb1:94b0:a95b",
        "latency": 3,
        "line": "CM",
        "loss": 0,
        "node": "NETCUP",
        "speed": 600,
        "time": "2026-05-20 19:39:18"
    },
    {
        "colo": "Default",
        "ip": "2606:4700:b:e210:3818:a7b5:3dff:4399",
        "latency": 13,
        "line": "CM",
        "loss": 0,
        "node": "NETCUP",
        "speed": 427,
        "time": "2026-05-20 19:39:18"
    },
    {
        "colo": "Default",
        "ip": "2606:4700:b:7405:754d:d73c:7abd:3dce",
        "latency": 3,
        "line": "CM",
        "loss": 0,
        "node": "NETCUP",
        "speed": 329,
        "time": "2026-05-20 19:39:18"
    },
    {
        "colo": "Default",
        "ip": "2606:4700:8dee:73aa:f2de:4495:403d:934a",
        "latency": 3,
        "line": "CM",
        "loss": 0,
        "node": "NETCUP",
        "speed": 327,
        "time": "2026-05-20 19:39:18"
    },
    {
        "colo": "Default",
        "ip": "2606:4700:91b6:411e:8d9:3aea:9090:c63c",
        "latency": 3,
        "line": "CM",
        "loss": 0,
        "node": "NETCUP",
        "speed": 315,
        "time": "2026-05-20 19:39:18"
    },
    {
        "colo": "Default",
        "ip": "2606:4700:8dee:b95e:2ae3:bfb1:94b0:a95b",
        "latency": 3,
        "line": "CT",
        "loss": 0,
        "node": "NETCUP",
        "speed": 600,
        "time": "2026-05-20 19:39:18"
    },
    {
        "colo": "Default",
        "ip": "2606:4700:b:e210:3818:a7b5:3dff:4399",
        "latency": 13,
        "line": "CT",
        "loss": 0,
        "node": "NETCUP",
        "speed": 427,
        "time": "2026-05-20 19:39:18"
    },
    {
        "colo": "Default",
        "ip": "2606:4700:b:7405:754d:d73c:7abd:3dce",
        "latency": 3,
        "line": "CT",
        "loss": 0,
        "node": "NETCUP",
        "speed": 329,
        "time": "2026-05-20 19:39:18"
    },
    {
        "colo": "Default",
        "ip": "2606:4700:8dee:73aa:f2de:4495:403d:934a",
        "latency": 3,
        "line": "CT",
        "loss": 0,
        "node": "NETCUP",
        "speed": 327,
        "time": "2026-05-20 19:39:18"
    },
    {
        "colo": "Default",
        "ip": "2606:4700:91b6:411e:8d9:3aea:9090:c63c",
        "latency": 3,
        "line": "CT",
        "loss": 0,
        "node": "NETCUP",
        "speed": 315,
        "time": "2026-05-20 19:39:18"
    },
    {
        "colo": "Default",
        "ip": "2606:4700:8dee:b95e:2ae3:bfb1:94b0:a95b",
        "latency": 3,
        "line": "CU",
        "loss": 0,
        "node": "NETCUP",
        "speed": 600,
        "time": "2026-05-20 19:39:18"
    },
    {
        "colo": "Default",
        "ip": "2606:4700:b:e210:3818:a7b5:3dff:4399",
        "latency": 13,
        "line": "CU",
        "loss": 0,
        "node": "NETCUP",
        "speed": 427,
        "time": "2026-05-20 19:39:18"
    },
    {
        "colo": "Default",
        "ip": "2606:4700:b:7405:754d:d73c:7abd:3dce",
        "latency": 3,
        "line": "CU",
        "loss": 0,
        "node": "NETCUP",
        "speed": 329,
        "time": "2026-05-20 19:39:18"
    },
    {
        "colo": "Default",
        "ip": "2606:4700:8dee:73aa:f2de:4495:403d:934a",
        "latency": 3,
        "line": "CU",
        "loss": 0,
        "node": "NETCUP",
        "speed": 327,
        "time": "2026-05-20 19:39:18"
    },
    {
        "colo": "Default",
        "ip": "2606:4700:91b6:411e:8d9:3aea:9090:c63c",
        "latency": 3,
        "line": "CU",
        "loss": 0,
        "node": "NETCUP",
        "speed": 315,
        "time": "2026-05-20 19:39:18"
    }
]