[
    {
        "colo": "Default",
        "ip": "2606:4700:8ca5:9f27:589e:46b9:633f:224e",
        "latency": 155,
        "line": "CM",
        "loss": 0,
        "node": "CBUS",
        "speed": 558,
        "time": "2024-10-23 03:13:17"
    },
    {
        "colo": "Default",
        "ip": "2606:4700:8ca5:b64c:346b:19dd:b9c5:3fe9",
        "latency": 149,
        "line": "CM",
        "loss": 0,
        "node": "CBUS",
        "speed": 556,
        "time": "2024-10-23 03:13:17"
    },
    {
        "colo": "Default",
        "ip": "2606:4700:8ca5:655f:d9d1:9560:4ed9:3e07",
        "latency": 155,
        "line": "CM",
        "loss": 0,
        "node": "CBUS",
        "speed": 539,
        "time": "2024-10-23 03:13:17"
    },
    {
        "colo": "Default",
        "ip": "2606:4700:8ca5:a903:883a:f028:850d:36ac",
        "latency": 155,
        "line": "CM",
        "loss": 0,
        "node": "CBUS",
        "speed": 417,
        "time": "2024-10-23 03:13:17"
    },
    {
        "colo": "Default",
        "ip": "2606:4700:e4:41d3:af6d:4bf:b4b4:d347",
        "latency": 29,
        "line": "CM",
        "loss": 0,
        "node": "CBUS",
        "speed": 310,
        "time": "2024-10-23 03:13:17"
    },
    {
        "colo": "Default",
        "ip": "2606:4700:131:ad31:e90a:c5bc:247d:d12a",
        "latency": 30,
        "line": "CT",
        "loss": 0,
        "node": "WEBH",
        "speed": 309,
        "time": "2024-10-23 03:05:31"
    },
    {
        "colo": "Default",
        "ip": "2606:4700:131:6fa6:45e2:401b:9ea6:68dc",
        "latency": 9,
        "line": "CT",
        "loss": 0,
        "node": "WEBH",
        "speed": 308,
        "time": "2024-10-23 03:05:31"
    },
    {
        "colo": "Default",
        "ip": "2606:4700:131:29e0:6494:9ae:5126:4832",
        "latency": 30,
        "line": "CT",
        "loss": 0,
        "node": "WEBH",
        "speed": 307,
        "time": "2024-10-23 03:05:32"
    },
    {
        "colo": "Default",
        "ip": "2606:4700:131:7056:c373:d1db:1cdd:a384",
        "latency": 9,
        "line": "CT",
        "loss": 0,
        "node": "WEBH",
        "speed": 307,
        "time": "2024-10-23 03:05:31"
    },
    {
        "colo": "Default",
        "ip": "2606:4700:131:2125:f27d:7052:48a:8a4a",
        "latency": 29,
        "line": "CT",
        "loss": 0,
        "node": "WEBH",
        "speed": 307,
        "time": "2024-10-23 03:05:31"
    },
    {
        "colo": "Default",
        "ip": "2606:4700:8ca5:9f27:589e:46b9:633f:224e",
        "latency": 155,
        "line": "CU",
        "loss": 0,
        "node": "CBUS",
        "speed": 558,
        "time": "2024-10-23 03:13:17"
    },
    {
        "colo": "Default",
        "ip": "2606:4700:8ca5:b64c:346b:19dd:b9c5:3fe9",
        "latency": 149,
        "line": "CU",
        "loss": 0,
        "node": "CBUS",
        "speed": 556,
        "time": "2024-10-23 03:13:17"
    },
    {
        "colo": "Default",
        "ip": "2606:4700:8ca5:655f:d9d1:9560:4ed9:3e07",
        "latency": 155,
        "line": "CU",
        "loss": 0,
        "node": "CBUS",
        "speed": 539,
        "time": "2024-10-23 03:13:17"
    },
    {
        "colo": "Default",
        "ip": "2606:4700:8ca5:a903:883a:f028:850d:36ac",
        "latency": 155,
        "line": "CU",
        "loss": 0,
        "node": "CBUS",
        "speed": 417,
        "time": "2024-10-23 03:13:17"
    },
    {
        "colo": "Default",
        "ip": "2606:4700:e4:41d3:af6d:4bf:b4b4:d347",
        "latency": 29,
        "line": "CU",
        "loss": 0,
        "node": "CBUS",
        "speed": 310,
        "time": "2024-10-23 03:13:17"
    }
]