[
    {
        "colo": "Default",
        "ip": "2606:4700:8de8:8f5d:cae9:a054:a4d1:9143",
        "latency": 4,
        "line": "CM",
        "loss": 0,
        "node": "NETCUP",
        "speed": 606,
        "time": "2025-09-27 19:49:50"
    },
    {
        "colo": "Default",
        "ip": "2606:4700:90c8:c9db:4256:8889:b45:4305",
        "latency": 3,
        "line": "CM",
        "loss": 0,
        "node": "NETCUP",
        "speed": 598,
        "time": "2025-09-27 19:49:50"
    },
    {
        "colo": "Default",
        "ip": "2606:4700:839b:d2c9:5260:82a8:b793:d08b",
        "latency": 4,
        "line": "CM",
        "loss": 0,
        "node": "NETCUP",
        "speed": 566,
        "time": "2025-09-27 19:49:50"
    },
    {
        "colo": "Default",
        "ip": "2606:4700:3022:adc0:c1e4:1606:3406:b22a",
        "latency": 13,
        "line": "CM",
        "loss": 0,
        "node": "NETCUP",
        "speed": 463,
        "time": "2025-09-27 19:49:50"
    },
    {
        "colo": "Default",
        "ip": "2606:4700:135:eaa1:3560:3b51:5b04:6cd5",
        "latency": 12,
        "line": "CM",
        "loss": 0,
        "node": "NETCUP",
        "speed": 435,
        "time": "2025-09-27 19:49:50"
    },
    {
        "colo": "Default",
        "ip": "2606:4700:8de8:8f5d:cae9:a054:a4d1:9143",
        "latency": 4,
        "line": "CT",
        "loss": 0,
        "node": "NETCUP",
        "speed": 606,
        "time": "2025-09-27 19:49:50"
    },
    {
        "colo": "Default",
        "ip": "2606:4700:90c8:c9db:4256:8889:b45:4305",
        "latency": 3,
        "line": "CT",
        "loss": 0,
        "node": "NETCUP",
        "speed": 598,
        "time": "2025-09-27 19:49:50"
    },
    {
        "colo": "Default",
        "ip": "2606:4700:839b:d2c9:5260:82a8:b793:d08b",
        "latency": 4,
        "line": "CT",
        "loss": 0,
        "node": "NETCUP",
        "speed": 566,
        "time": "2025-09-27 19:49:50"
    },
    {
        "colo": "Default",
        "ip": "2606:4700:3022:adc0:c1e4:1606:3406:b22a",
        "latency": 13,
        "line": "CT",
        "loss": 0,
        "node": "NETCUP",
        "speed": 463,
        "time": "2025-09-27 19:49:50"
    },
    {
        "colo": "Default",
        "ip": "2606:4700:135:eaa1:3560:3b51:5b04:6cd5",
        "latency": 12,
        "line": "CT",
        "loss": 0,
        "node": "NETCUP",
        "speed": 435,
        "time": "2025-09-27 19:49:50"
    },
    {
        "colo": "Default",
        "ip": "2606:4700:8de8:8f5d:cae9:a054:a4d1:9143",
        "latency": 4,
        "line": "CU",
        "loss": 0,
        "node": "NETCUP",
        "speed": 606,
        "time": "2025-09-27 19:49:50"
    },
    {
        "colo": "Default",
        "ip": "2606:4700:90c8:c9db:4256:8889:b45:4305",
        "latency": 3,
        "line": "CU",
        "loss": 0,
        "node": "NETCUP",
        "speed": 598,
        "time": "2025-09-27 19:49:50"
    },
    {
        "colo": "Default",
        "ip": "2606:4700:839b:d2c9:5260:82a8:b793:d08b",
        "latency": 4,
        "line": "CU",
        "loss": 0,
        "node": "NETCUP",
        "speed": 566,
        "time": "2025-09-27 19:49:50"
    },
    {
        "colo": "Default",
        "ip": "2606:4700:3022:adc0:c1e4:1606:3406:b22a",
        "latency": 13,
        "line": "CU",
        "loss": 0,
        "node": "NETCUP",
        "speed": 463,
        "time": "2025-09-27 19:49:50"
    },
    {
        "colo": "Default",
        "ip": "2606:4700:135:eaa1:3560:3b51:5b04:6cd5",
        "latency": 12,
        "line": "CU",
        "loss": 0,
        "node": "NETCUP",
        "speed": 435,
        "time": "2025-09-27 19:49:50"
    }
]