[
    {
        "colo": "Default",
        "ip": "2606:4700:14:af01:11e:6f59:1d5f:efb8",
        "latency": 11,
        "line": "CM",
        "loss": 0,
        "node": "CBUS",
        "speed": 622,
        "time": "2024-09-14 11:27:24"
    },
    {
        "colo": "Default",
        "ip": "2606:4700:14:9c8e:b7c7:503f:be66:bb25",
        "latency": 12,
        "line": "CM",
        "loss": 0,
        "node": "CBUS",
        "speed": 548,
        "time": "2024-09-14 11:27:24"
    },
    {
        "colo": "Default",
        "ip": "2606:4700:14:8528:206d:f353:c338:2dd3",
        "latency": 11,
        "line": "CM",
        "loss": 0,
        "node": "CBUS",
        "speed": 532,
        "time": "2024-09-14 11:27:24"
    },
    {
        "colo": "Default",
        "ip": "2606:4700:14:146b:74d7:7e2e:835f:4314",
        "latency": 11,
        "line": "CM",
        "loss": 0,
        "node": "CBUS",
        "speed": 525,
        "time": "2024-09-14 11:27:24"
    },
    {
        "colo": "Default",
        "ip": "2606:4700:14:3e28:b18d:93ac:225a:564d",
        "latency": 12,
        "line": "CM",
        "loss": 0,
        "node": "CBUS",
        "speed": 523,
        "time": "2024-09-14 11:27:24"
    },
    {
        "colo": "Default",
        "ip": "2606:4700:91b1:17a5:ac96:5069:39e5:a11c",
        "latency": 20,
        "line": "CT",
        "loss": 0,
        "node": "WEBH",
        "speed": 310,
        "time": "2024-09-14 11:25:57"
    },
    {
        "colo": "Default",
        "ip": "2606:4700:8d99:fa69:5318:c1ba:5285:681d",
        "latency": 25,
        "line": "CT",
        "loss": 0,
        "node": "WEBH",
        "speed": 309,
        "time": "2024-09-14 11:26:00"
    },
    {
        "colo": "Default",
        "ip": "2606:4700:91b1:643b:baab:497e:dc0e:66d6",
        "latency": 20,
        "line": "CT",
        "loss": 0,
        "node": "WEBH",
        "speed": 309,
        "time": "2024-09-14 11:25:59"
    },
    {
        "colo": "Default",
        "ip": "2606:4700:91b1:3c8d:6f74:3f7f:68ad:f14",
        "latency": 20,
        "line": "CT",
        "loss": 0,
        "node": "WEBH",
        "speed": 308,
        "time": "2024-09-14 11:25:58"
    },
    {
        "colo": "Default",
        "ip": "2606:4700:91b1:4b1d:79af:ac7c:e38b:61e0",
        "latency": 23,
        "line": "CT",
        "loss": 0,
        "node": "WEBH",
        "speed": 307,
        "time": "2024-09-14 11:26:00"
    },
    {
        "colo": "Default",
        "ip": "2606:4700:14:af01:11e:6f59:1d5f:efb8",
        "latency": 11,
        "line": "CU",
        "loss": 0,
        "node": "CBUS",
        "speed": 622,
        "time": "2024-09-14 11:27:24"
    },
    {
        "colo": "Default",
        "ip": "2606:4700:14:9c8e:b7c7:503f:be66:bb25",
        "latency": 12,
        "line": "CU",
        "loss": 0,
        "node": "CBUS",
        "speed": 548,
        "time": "2024-09-14 11:27:24"
    },
    {
        "colo": "Default",
        "ip": "2606:4700:14:8528:206d:f353:c338:2dd3",
        "latency": 11,
        "line": "CU",
        "loss": 0,
        "node": "CBUS",
        "speed": 532,
        "time": "2024-09-14 11:27:24"
    },
    {
        "colo": "Default",
        "ip": "2606:4700:14:146b:74d7:7e2e:835f:4314",
        "latency": 11,
        "line": "CU",
        "loss": 0,
        "node": "CBUS",
        "speed": 525,
        "time": "2024-09-14 11:27:24"
    },
    {
        "colo": "Default",
        "ip": "2606:4700:14:3e28:b18d:93ac:225a:564d",
        "latency": 12,
        "line": "CU",
        "loss": 0,
        "node": "CBUS",
        "speed": 523,
        "time": "2024-09-14 11:27:24"
    }
]