[
    {
        "colo": "Default",
        "ip": "2606:4700:9b07:e79b:b684:1cd2:18d:1e83",
        "latency": 9,
        "line": "CM",
        "loss": 0,
        "node": "NETCUP",
        "speed": 535,
        "time": "2025-12-21 13:29:18"
    },
    {
        "colo": "Default",
        "ip": "2606:4700:9641:826e:9fab:f627:b505:56f8",
        "latency": 8,
        "line": "CM",
        "loss": 0,
        "node": "NETCUP",
        "speed": 494,
        "time": "2025-12-21 13:29:18"
    },
    {
        "colo": "Default",
        "ip": "2606:4700:3000:525:f9e4:24f:4a82:1f4c",
        "latency": 3,
        "line": "CM",
        "loss": 0,
        "node": "NETCUP",
        "speed": 429,
        "time": "2025-12-21 13:29:18"
    },
    {
        "colo": "Default",
        "ip": "2606:4700:91bf:e603:e7a2:e1d3:8b89:9090",
        "latency": 9,
        "line": "CM",
        "loss": 0,
        "node": "NETCUP",
        "speed": 424,
        "time": "2025-12-21 13:29:18"
    },
    {
        "colo": "Default",
        "ip": "2606:4700:9641:1baf:20cd:e2aa:3b9b:e343",
        "latency": 9,
        "line": "CM",
        "loss": 0,
        "node": "NETCUP",
        "speed": 418,
        "time": "2025-12-21 13:29:18"
    },
    {
        "colo": "Default",
        "ip": "2606:4700:9b07:e79b:b684:1cd2:18d:1e83",
        "latency": 9,
        "line": "CT",
        "loss": 0,
        "node": "NETCUP",
        "speed": 535,
        "time": "2025-12-21 13:29:18"
    },
    {
        "colo": "Default",
        "ip": "2606:4700:9641:826e:9fab:f627:b505:56f8",
        "latency": 8,
        "line": "CT",
        "loss": 0,
        "node": "NETCUP",
        "speed": 494,
        "time": "2025-12-21 13:29:18"
    },
    {
        "colo": "Default",
        "ip": "2606:4700:3000:525:f9e4:24f:4a82:1f4c",
        "latency": 3,
        "line": "CT",
        "loss": 0,
        "node": "NETCUP",
        "speed": 429,
        "time": "2025-12-21 13:29:18"
    },
    {
        "colo": "Default",
        "ip": "2606:4700:91bf:e603:e7a2:e1d3:8b89:9090",
        "latency": 9,
        "line": "CT",
        "loss": 0,
        "node": "NETCUP",
        "speed": 424,
        "time": "2025-12-21 13:29:18"
    },
    {
        "colo": "Default",
        "ip": "2606:4700:9641:1baf:20cd:e2aa:3b9b:e343",
        "latency": 9,
        "line": "CT",
        "loss": 0,
        "node": "NETCUP",
        "speed": 418,
        "time": "2025-12-21 13:29:18"
    },
    {
        "colo": "Default",
        "ip": "2606:4700:9b07:e79b:b684:1cd2:18d:1e83",
        "latency": 9,
        "line": "CU",
        "loss": 0,
        "node": "NETCUP",
        "speed": 535,
        "time": "2025-12-21 13:29:18"
    },
    {
        "colo": "Default",
        "ip": "2606:4700:9641:826e:9fab:f627:b505:56f8",
        "latency": 8,
        "line": "CU",
        "loss": 0,
        "node": "NETCUP",
        "speed": 494,
        "time": "2025-12-21 13:29:18"
    },
    {
        "colo": "Default",
        "ip": "2606:4700:3000:525:f9e4:24f:4a82:1f4c",
        "latency": 3,
        "line": "CU",
        "loss": 0,
        "node": "NETCUP",
        "speed": 429,
        "time": "2025-12-21 13:29:18"
    },
    {
        "colo": "Default",
        "ip": "2606:4700:91bf:e603:e7a2:e1d3:8b89:9090",
        "latency": 9,
        "line": "CU",
        "loss": 0,
        "node": "NETCUP",
        "speed": 424,
        "time": "2025-12-21 13:29:18"
    },
    {
        "colo": "Default",
        "ip": "2606:4700:9641:1baf:20cd:e2aa:3b9b:e343",
        "latency": 9,
        "line": "CU",
        "loss": 0,
        "node": "NETCUP",
        "speed": 418,
        "time": "2025-12-21 13:29:18"
    }
]