[
    {
        "colo": "Default",
        "ip": "2606:4700:9646:f61e:96cc:206c:787f:26f4",
        "latency": 4,
        "line": "CM",
        "loss": 0,
        "node": "NETCUP",
        "speed": 530,
        "time": "2025-08-21 17:39:51"
    },
    {
        "colo": "Default",
        "ip": "2606:4700:9c61:cb2c:776c:9ec4:877d:c467",
        "latency": 4,
        "line": "CM",
        "loss": 0,
        "node": "NETCUP",
        "speed": 452,
        "time": "2025-08-21 17:39:52"
    },
    {
        "colo": "Default",
        "ip": "2606:4700:9c61:fc3:c93a:b354:cf9c:ddd6",
        "latency": 4,
        "line": "CM",
        "loss": 0,
        "node": "NETCUP",
        "speed": 380,
        "time": "2025-08-21 17:39:51"
    },
    {
        "colo": "Default",
        "ip": "2606:4700:9a9c:70d1:71a:c40:c77e:a0b0",
        "latency": 3,
        "line": "CM",
        "loss": 0,
        "node": "NETCUP",
        "speed": 373,
        "time": "2025-08-21 17:39:51"
    },
    {
        "colo": "Default",
        "ip": "2606:4700:9646:c1b7:7b0f:e48b:dcc4:d893",
        "latency": 4,
        "line": "CM",
        "loss": 0,
        "node": "NETCUP",
        "speed": 367,
        "time": "2025-08-21 17:39:51"
    },
    {
        "colo": "Default",
        "ip": "2606:4700:9646:f61e:96cc:206c:787f:26f4",
        "latency": 4,
        "line": "CT",
        "loss": 0,
        "node": "NETCUP",
        "speed": 530,
        "time": "2025-08-21 17:39:51"
    },
    {
        "colo": "Default",
        "ip": "2606:4700:9c61:cb2c:776c:9ec4:877d:c467",
        "latency": 4,
        "line": "CT",
        "loss": 0,
        "node": "NETCUP",
        "speed": 452,
        "time": "2025-08-21 17:39:52"
    },
    {
        "colo": "Default",
        "ip": "2606:4700:9c61:fc3:c93a:b354:cf9c:ddd6",
        "latency": 4,
        "line": "CT",
        "loss": 0,
        "node": "NETCUP",
        "speed": 380,
        "time": "2025-08-21 17:39:51"
    },
    {
        "colo": "Default",
        "ip": "2606:4700:9a9c:70d1:71a:c40:c77e:a0b0",
        "latency": 3,
        "line": "CT",
        "loss": 0,
        "node": "NETCUP",
        "speed": 373,
        "time": "2025-08-21 17:39:51"
    },
    {
        "colo": "Default",
        "ip": "2606:4700:9646:c1b7:7b0f:e48b:dcc4:d893",
        "latency": 4,
        "line": "CT",
        "loss": 0,
        "node": "NETCUP",
        "speed": 367,
        "time": "2025-08-21 17:39:51"
    },
    {
        "colo": "Default",
        "ip": "2606:4700:9646:f61e:96cc:206c:787f:26f4",
        "latency": 4,
        "line": "CU",
        "loss": 0,
        "node": "NETCUP",
        "speed": 530,
        "time": "2025-08-21 17:39:51"
    },
    {
        "colo": "Default",
        "ip": "2606:4700:9c61:cb2c:776c:9ec4:877d:c467",
        "latency": 4,
        "line": "CU",
        "loss": 0,
        "node": "NETCUP",
        "speed": 452,
        "time": "2025-08-21 17:39:52"
    },
    {
        "colo": "Default",
        "ip": "2606:4700:9c61:fc3:c93a:b354:cf9c:ddd6",
        "latency": 4,
        "line": "CU",
        "loss": 0,
        "node": "NETCUP",
        "speed": 380,
        "time": "2025-08-21 17:39:51"
    },
    {
        "colo": "Default",
        "ip": "2606:4700:9a9c:70d1:71a:c40:c77e:a0b0",
        "latency": 3,
        "line": "CU",
        "loss": 0,
        "node": "NETCUP",
        "speed": 373,
        "time": "2025-08-21 17:39:51"
    },
    {
        "colo": "Default",
        "ip": "2606:4700:9646:c1b7:7b0f:e48b:dcc4:d893",
        "latency": 4,
        "line": "CU",
        "loss": 0,
        "node": "NETCUP",
        "speed": 367,
        "time": "2025-08-21 17:39:51"
    }
]