[
    {
        "colo": "Default",
        "ip": "2606:4700:9ad3:3e97:bbd2:e124:2b3:bb02",
        "latency": 3,
        "line": "CM",
        "loss": 0,
        "node": "NETCUP",
        "speed": 444,
        "time": "2025-11-05 02:19:51"
    },
    {
        "colo": "Default",
        "ip": "2606:4700:9ad3:c5bf:9010:ec90:d2f2:2a05",
        "latency": 3,
        "line": "CM",
        "loss": 0,
        "node": "NETCUP",
        "speed": 434,
        "time": "2025-11-05 02:19:51"
    },
    {
        "colo": "Default",
        "ip": "2606:4700:8d98:3f03:8908:e89f:9f20:a92c",
        "latency": 3,
        "line": "CM",
        "loss": 0,
        "node": "NETCUP",
        "speed": 394,
        "time": "2025-11-05 02:19:51"
    },
    {
        "colo": "Default",
        "ip": "2606:4700:8de3:b88b:24ce:d119:dd77:5ac5",
        "latency": 3,
        "line": "CM",
        "loss": 0,
        "node": "NETCUP",
        "speed": 342,
        "time": "2025-11-05 02:19:51"
    },
    {
        "colo": "Default",
        "ip": "2606:4700:8d90:ab41:43a0:c89:2a4c:3508",
        "latency": 3,
        "line": "CM",
        "loss": 0,
        "node": "NETCUP",
        "speed": 308,
        "time": "2025-11-05 02:19:52"
    },
    {
        "colo": "Default",
        "ip": "2606:4700:9ad3:3e97:bbd2:e124:2b3:bb02",
        "latency": 3,
        "line": "CT",
        "loss": 0,
        "node": "NETCUP",
        "speed": 444,
        "time": "2025-11-05 02:19:51"
    },
    {
        "colo": "Default",
        "ip": "2606:4700:9ad3:c5bf:9010:ec90:d2f2:2a05",
        "latency": 3,
        "line": "CT",
        "loss": 0,
        "node": "NETCUP",
        "speed": 434,
        "time": "2025-11-05 02:19:51"
    },
    {
        "colo": "Default",
        "ip": "2606:4700:8d98:3f03:8908:e89f:9f20:a92c",
        "latency": 3,
        "line": "CT",
        "loss": 0,
        "node": "NETCUP",
        "speed": 394,
        "time": "2025-11-05 02:19:51"
    },
    {
        "colo": "Default",
        "ip": "2606:4700:8de3:b88b:24ce:d119:dd77:5ac5",
        "latency": 3,
        "line": "CT",
        "loss": 0,
        "node": "NETCUP",
        "speed": 342,
        "time": "2025-11-05 02:19:51"
    },
    {
        "colo": "Default",
        "ip": "2606:4700:8d90:ab41:43a0:c89:2a4c:3508",
        "latency": 3,
        "line": "CT",
        "loss": 0,
        "node": "NETCUP",
        "speed": 308,
        "time": "2025-11-05 02:19:52"
    },
    {
        "colo": "Default",
        "ip": "2606:4700:9ad3:3e97:bbd2:e124:2b3:bb02",
        "latency": 3,
        "line": "CU",
        "loss": 0,
        "node": "NETCUP",
        "speed": 444,
        "time": "2025-11-05 02:19:51"
    },
    {
        "colo": "Default",
        "ip": "2606:4700:9ad3:c5bf:9010:ec90:d2f2:2a05",
        "latency": 3,
        "line": "CU",
        "loss": 0,
        "node": "NETCUP",
        "speed": 434,
        "time": "2025-11-05 02:19:51"
    },
    {
        "colo": "Default",
        "ip": "2606:4700:8d98:3f03:8908:e89f:9f20:a92c",
        "latency": 3,
        "line": "CU",
        "loss": 0,
        "node": "NETCUP",
        "speed": 394,
        "time": "2025-11-05 02:19:51"
    },
    {
        "colo": "Default",
        "ip": "2606:4700:8de3:b88b:24ce:d119:dd77:5ac5",
        "latency": 3,
        "line": "CU",
        "loss": 0,
        "node": "NETCUP",
        "speed": 342,
        "time": "2025-11-05 02:19:51"
    },
    {
        "colo": "Default",
        "ip": "2606:4700:8d90:ab41:43a0:c89:2a4c:3508",
        "latency": 3,
        "line": "CU",
        "loss": 0,
        "node": "NETCUP",
        "speed": 308,
        "time": "2025-11-05 02:19:52"
    }
]