[
    {
        "colo": "Default",
        "ip": "2606:4700:4407:6ba9:ae67:6194:cce1:f951",
        "latency": 3,
        "line": "CM",
        "loss": 0,
        "node": "NETCUP",
        "speed": 500,
        "time": "2025-09-12 16:39:49"
    },
    {
        "colo": "Default",
        "ip": "2606:4700:9a9e:5983:444e:ba20:a324:4bc0",
        "latency": 3,
        "line": "CM",
        "loss": 0,
        "node": "NETCUP",
        "speed": 385,
        "time": "2025-09-12 16:39:49"
    },
    {
        "colo": "Default",
        "ip": "2606:4700:4401:5c4a:8253:df63:848a:7eaa",
        "latency": 4,
        "line": "CM",
        "loss": 0,
        "node": "NETCUP",
        "speed": 374,
        "time": "2025-09-12 16:39:49"
    },
    {
        "colo": "Default",
        "ip": "2606:4700:9a9e:6fab:5062:fe84:40eb:c582",
        "latency": 4,
        "line": "CM",
        "loss": 0,
        "node": "NETCUP",
        "speed": 371,
        "time": "2025-09-12 16:39:49"
    },
    {
        "colo": "Default",
        "ip": "2606:4700:4407:259a:8216:aab4:d2c6:ce27",
        "latency": 4,
        "line": "CM",
        "loss": 0,
        "node": "NETCUP",
        "speed": 347,
        "time": "2025-09-12 16:39:49"
    },
    {
        "colo": "Default",
        "ip": "2606:4700:4407:6ba9:ae67:6194:cce1:f951",
        "latency": 3,
        "line": "CT",
        "loss": 0,
        "node": "NETCUP",
        "speed": 500,
        "time": "2025-09-12 16:39:49"
    },
    {
        "colo": "Default",
        "ip": "2606:4700:9a9e:5983:444e:ba20:a324:4bc0",
        "latency": 3,
        "line": "CT",
        "loss": 0,
        "node": "NETCUP",
        "speed": 385,
        "time": "2025-09-12 16:39:49"
    },
    {
        "colo": "Default",
        "ip": "2606:4700:4401:5c4a:8253:df63:848a:7eaa",
        "latency": 4,
        "line": "CT",
        "loss": 0,
        "node": "NETCUP",
        "speed": 374,
        "time": "2025-09-12 16:39:49"
    },
    {
        "colo": "Default",
        "ip": "2606:4700:9a9e:6fab:5062:fe84:40eb:c582",
        "latency": 4,
        "line": "CT",
        "loss": 0,
        "node": "NETCUP",
        "speed": 371,
        "time": "2025-09-12 16:39:49"
    },
    {
        "colo": "Default",
        "ip": "2606:4700:4407:259a:8216:aab4:d2c6:ce27",
        "latency": 4,
        "line": "CT",
        "loss": 0,
        "node": "NETCUP",
        "speed": 347,
        "time": "2025-09-12 16:39:49"
    },
    {
        "colo": "Default",
        "ip": "2606:4700:4407:6ba9:ae67:6194:cce1:f951",
        "latency": 3,
        "line": "CU",
        "loss": 0,
        "node": "NETCUP",
        "speed": 500,
        "time": "2025-09-12 16:39:49"
    },
    {
        "colo": "Default",
        "ip": "2606:4700:9a9e:5983:444e:ba20:a324:4bc0",
        "latency": 3,
        "line": "CU",
        "loss": 0,
        "node": "NETCUP",
        "speed": 385,
        "time": "2025-09-12 16:39:49"
    },
    {
        "colo": "Default",
        "ip": "2606:4700:4401:5c4a:8253:df63:848a:7eaa",
        "latency": 4,
        "line": "CU",
        "loss": 0,
        "node": "NETCUP",
        "speed": 374,
        "time": "2025-09-12 16:39:49"
    },
    {
        "colo": "Default",
        "ip": "2606:4700:9a9e:6fab:5062:fe84:40eb:c582",
        "latency": 4,
        "line": "CU",
        "loss": 0,
        "node": "NETCUP",
        "speed": 371,
        "time": "2025-09-12 16:39:49"
    },
    {
        "colo": "Default",
        "ip": "2606:4700:4407:259a:8216:aab4:d2c6:ce27",
        "latency": 4,
        "line": "CU",
        "loss": 0,
        "node": "NETCUP",
        "speed": 347,
        "time": "2025-09-12 16:39:49"
    }
]