[
    {
        "colo": "Default",
        "ip": "2606:4700:2a:8234:2209:d935:1ba9:b6e2",
        "latency": 1,
        "line": "CM",
        "loss": 20,
        "node": "PROHOSTING24",
        "speed": 572,
        "time": "2026-03-11 23:09:15"
    },
    {
        "colo": "Default",
        "ip": "2606:4700:3027:5c2a:1638:8bb:1480:b521",
        "latency": 1,
        "line": "CM",
        "loss": 20,
        "node": "PROHOSTING24",
        "speed": 514,
        "time": "2026-03-11 23:09:15"
    },
    {
        "colo": "Default",
        "ip": "2606:4700:132:435e:186b:67d:8106:1cf7",
        "latency": 1,
        "line": "CM",
        "loss": 20,
        "node": "PROHOSTING24",
        "speed": 371,
        "time": "2026-03-11 23:09:15"
    },
    {
        "colo": "Default",
        "ip": "2606:4700:99e3:c336:aef7:2b8b:34e6:80d1",
        "latency": 3,
        "line": "CM",
        "loss": 0,
        "node": "NETCUP",
        "speed": 321,
        "time": "2026-03-11 22:59:17"
    },
    {
        "colo": "Default",
        "ip": "2606:4700:138:1efb:42a7:43f2:b927:2c89",
        "latency": 1,
        "line": "CM",
        "loss": 20,
        "node": "PROHOSTING24",
        "speed": 321,
        "time": "2026-03-11 23:09:15"
    },
    {
        "colo": "Default",
        "ip": "2606:4700:2a:8234:2209:d935:1ba9:b6e2",
        "latency": 1,
        "line": "CT",
        "loss": 20,
        "node": "PROHOSTING24",
        "speed": 572,
        "time": "2026-03-11 23:09:15"
    },
    {
        "colo": "Default",
        "ip": "2606:4700:3027:5c2a:1638:8bb:1480:b521",
        "latency": 1,
        "line": "CT",
        "loss": 20,
        "node": "PROHOSTING24",
        "speed": 514,
        "time": "2026-03-11 23:09:15"
    },
    {
        "colo": "Default",
        "ip": "2606:4700:132:435e:186b:67d:8106:1cf7",
        "latency": 1,
        "line": "CT",
        "loss": 20,
        "node": "PROHOSTING24",
        "speed": 371,
        "time": "2026-03-11 23:09:15"
    },
    {
        "colo": "Default",
        "ip": "2606:4700:99e3:c336:aef7:2b8b:34e6:80d1",
        "latency": 3,
        "line": "CT",
        "loss": 0,
        "node": "NETCUP",
        "speed": 321,
        "time": "2026-03-11 22:59:17"
    },
    {
        "colo": "Default",
        "ip": "2606:4700:138:1efb:42a7:43f2:b927:2c89",
        "latency": 1,
        "line": "CT",
        "loss": 20,
        "node": "PROHOSTING24",
        "speed": 321,
        "time": "2026-03-11 23:09:15"
    },
    {
        "colo": "Default",
        "ip": "2606:4700:2a:8234:2209:d935:1ba9:b6e2",
        "latency": 1,
        "line": "CU",
        "loss": 20,
        "node": "PROHOSTING24",
        "speed": 572,
        "time": "2026-03-11 23:09:15"
    },
    {
        "colo": "Default",
        "ip": "2606:4700:3027:5c2a:1638:8bb:1480:b521",
        "latency": 1,
        "line": "CU",
        "loss": 20,
        "node": "PROHOSTING24",
        "speed": 514,
        "time": "2026-03-11 23:09:15"
    },
    {
        "colo": "Default",
        "ip": "2606:4700:132:435e:186b:67d:8106:1cf7",
        "latency": 1,
        "line": "CU",
        "loss": 20,
        "node": "PROHOSTING24",
        "speed": 371,
        "time": "2026-03-11 23:09:15"
    },
    {
        "colo": "Default",
        "ip": "2606:4700:99e3:c336:aef7:2b8b:34e6:80d1",
        "latency": 3,
        "line": "CU",
        "loss": 0,
        "node": "NETCUP",
        "speed": 321,
        "time": "2026-03-11 22:59:17"
    },
    {
        "colo": "Default",
        "ip": "2606:4700:138:1efb:42a7:43f2:b927:2c89",
        "latency": 1,
        "line": "CU",
        "loss": 20,
        "node": "PROHOSTING24",
        "speed": 321,
        "time": "2026-03-11 23:09:15"
    }
]