[
    {
        "colo": "Default",
        "ip": "2606:4700:83b1:db94:7670:4409:bd1a:fbe0",
        "latency": 149,
        "line": "CM",
        "loss": 0,
        "node": "NETCUP",
        "speed": 620,
        "time": "2025-05-14 02:44:29"
    },
    {
        "colo": "Default",
        "ip": "2606:4700:83b1:2bb9:1f60:edb2:6970:bda5",
        "latency": 138,
        "line": "CM",
        "loss": 0,
        "node": "NETCUP",
        "speed": 507,
        "time": "2025-05-14 02:44:29"
    },
    {
        "colo": "Default",
        "ip": "2606:4700:91bf:cec3:fa7c:e2cc:9220:2798",
        "latency": 3,
        "line": "CM",
        "loss": 0,
        "node": "NETCUP",
        "speed": 453,
        "time": "2025-05-14 02:44:29"
    },
    {
        "colo": "Default",
        "ip": "2606:4700:90c4:f56d:2b23:47f7:6fcf:fd39",
        "latency": 4,
        "line": "CM",
        "loss": 0,
        "node": "NETCUP",
        "speed": 449,
        "time": "2025-05-14 02:44:28"
    },
    {
        "colo": "Default",
        "ip": "2606:4700:91b9:eb4d:31cd:c3f8:e9a6:b81e",
        "latency": 4,
        "line": "CM",
        "loss": 0,
        "node": "NETCUP",
        "speed": 398,
        "time": "2025-05-14 02:44:28"
    },
    {
        "colo": "Default",
        "ip": "2606:4700:83b1:db94:7670:4409:bd1a:fbe0",
        "latency": 149,
        "line": "CT",
        "loss": 0,
        "node": "NETCUP",
        "speed": 620,
        "time": "2025-05-14 02:44:29"
    },
    {
        "colo": "Default",
        "ip": "2606:4700:83b1:2bb9:1f60:edb2:6970:bda5",
        "latency": 138,
        "line": "CT",
        "loss": 0,
        "node": "NETCUP",
        "speed": 507,
        "time": "2025-05-14 02:44:29"
    },
    {
        "colo": "Default",
        "ip": "2606:4700:91bf:cec3:fa7c:e2cc:9220:2798",
        "latency": 3,
        "line": "CT",
        "loss": 0,
        "node": "NETCUP",
        "speed": 453,
        "time": "2025-05-14 02:44:29"
    },
    {
        "colo": "Default",
        "ip": "2606:4700:90c4:f56d:2b23:47f7:6fcf:fd39",
        "latency": 4,
        "line": "CT",
        "loss": 0,
        "node": "NETCUP",
        "speed": 449,
        "time": "2025-05-14 02:44:28"
    },
    {
        "colo": "Default",
        "ip": "2606:4700:91b9:eb4d:31cd:c3f8:e9a6:b81e",
        "latency": 4,
        "line": "CT",
        "loss": 0,
        "node": "NETCUP",
        "speed": 398,
        "time": "2025-05-14 02:44:28"
    },
    {
        "colo": "Default",
        "ip": "2606:4700:83b1:db94:7670:4409:bd1a:fbe0",
        "latency": 149,
        "line": "CU",
        "loss": 0,
        "node": "NETCUP",
        "speed": 620,
        "time": "2025-05-14 02:44:29"
    },
    {
        "colo": "Default",
        "ip": "2606:4700:83b1:2bb9:1f60:edb2:6970:bda5",
        "latency": 138,
        "line": "CU",
        "loss": 0,
        "node": "NETCUP",
        "speed": 507,
        "time": "2025-05-14 02:44:29"
    },
    {
        "colo": "Default",
        "ip": "2606:4700:91bf:cec3:fa7c:e2cc:9220:2798",
        "latency": 3,
        "line": "CU",
        "loss": 0,
        "node": "NETCUP",
        "speed": 453,
        "time": "2025-05-14 02:44:29"
    },
    {
        "colo": "Default",
        "ip": "2606:4700:90c4:f56d:2b23:47f7:6fcf:fd39",
        "latency": 4,
        "line": "CU",
        "loss": 0,
        "node": "NETCUP",
        "speed": 449,
        "time": "2025-05-14 02:44:28"
    },
    {
        "colo": "Default",
        "ip": "2606:4700:91b9:eb4d:31cd:c3f8:e9a6:b81e",
        "latency": 4,
        "line": "CU",
        "loss": 0,
        "node": "NETCUP",
        "speed": 398,
        "time": "2025-05-14 02:44:28"
    }
]