[
    {
        "colo": "Default",
        "ip": "2606:4700:2b:84e2:16b1:fc05:880c:30ad",
        "latency": 3,
        "line": "CM",
        "loss": 0,
        "node": "NETCUP",
        "speed": 458,
        "time": "2025-06-03 11:05:39"
    },
    {
        "colo": "Default",
        "ip": "2606:4700:9a68:85c9:d6b4:c117:b047:72b4",
        "latency": 3,
        "line": "CM",
        "loss": 0,
        "node": "NETCUP",
        "speed": 431,
        "time": "2025-06-03 11:05:39"
    },
    {
        "colo": "Default",
        "ip": "2606:4700:90d9:9d2e:7565:511b:2742:93de",
        "latency": 3,
        "line": "CM",
        "loss": 0,
        "node": "NETCUP",
        "speed": 404,
        "time": "2025-06-03 11:05:39"
    },
    {
        "colo": "Default",
        "ip": "2606:4700:3055:a7e0:a0ec:1401:9693:469e",
        "latency": 4,
        "line": "CM",
        "loss": 0,
        "node": "NETCUP",
        "speed": 400,
        "time": "2025-06-03 11:05:39"
    },
    {
        "colo": "Default",
        "ip": "2606:4700:91ba:271f:d62e:9873:bc6a:27",
        "latency": 4,
        "line": "CM",
        "loss": 0,
        "node": "NETCUP",
        "speed": 385,
        "time": "2025-06-03 11:05:39"
    },
    {
        "colo": "Default",
        "ip": "2606:4700:2b:84e2:16b1:fc05:880c:30ad",
        "latency": 3,
        "line": "CT",
        "loss": 0,
        "node": "NETCUP",
        "speed": 458,
        "time": "2025-06-03 11:05:39"
    },
    {
        "colo": "Default",
        "ip": "2606:4700:9a68:85c9:d6b4:c117:b047:72b4",
        "latency": 3,
        "line": "CT",
        "loss": 0,
        "node": "NETCUP",
        "speed": 431,
        "time": "2025-06-03 11:05:39"
    },
    {
        "colo": "Default",
        "ip": "2606:4700:90d9:9d2e:7565:511b:2742:93de",
        "latency": 3,
        "line": "CT",
        "loss": 0,
        "node": "NETCUP",
        "speed": 404,
        "time": "2025-06-03 11:05:39"
    },
    {
        "colo": "Default",
        "ip": "2606:4700:3055:a7e0:a0ec:1401:9693:469e",
        "latency": 4,
        "line": "CT",
        "loss": 0,
        "node": "NETCUP",
        "speed": 400,
        "time": "2025-06-03 11:05:39"
    },
    {
        "colo": "Default",
        "ip": "2606:4700:91ba:271f:d62e:9873:bc6a:27",
        "latency": 4,
        "line": "CT",
        "loss": 0,
        "node": "NETCUP",
        "speed": 385,
        "time": "2025-06-03 11:05:39"
    },
    {
        "colo": "Default",
        "ip": "2606:4700:2b:84e2:16b1:fc05:880c:30ad",
        "latency": 3,
        "line": "CU",
        "loss": 0,
        "node": "NETCUP",
        "speed": 458,
        "time": "2025-06-03 11:05:39"
    },
    {
        "colo": "Default",
        "ip": "2606:4700:9a68:85c9:d6b4:c117:b047:72b4",
        "latency": 3,
        "line": "CU",
        "loss": 0,
        "node": "NETCUP",
        "speed": 431,
        "time": "2025-06-03 11:05:39"
    },
    {
        "colo": "Default",
        "ip": "2606:4700:90d9:9d2e:7565:511b:2742:93de",
        "latency": 3,
        "line": "CU",
        "loss": 0,
        "node": "NETCUP",
        "speed": 404,
        "time": "2025-06-03 11:05:39"
    },
    {
        "colo": "Default",
        "ip": "2606:4700:3055:a7e0:a0ec:1401:9693:469e",
        "latency": 4,
        "line": "CU",
        "loss": 0,
        "node": "NETCUP",
        "speed": 400,
        "time": "2025-06-03 11:05:39"
    },
    {
        "colo": "Default",
        "ip": "2606:4700:91ba:271f:d62e:9873:bc6a:27",
        "latency": 4,
        "line": "CU",
        "loss": 0,
        "node": "NETCUP",
        "speed": 385,
        "time": "2025-06-03 11:05:39"
    }
]